doudesu/__init__.py
doudesu/__main__.py
doudesu/api/__init__.py
doudesu/assets/favicon.png
doudesu/assets/icons/icon-192.png
doudesu/assets/icons/icon-512.png
doudesu/assets/icons/icon-maskable-192.png
doudesu/assets/icons/icon-maskable-512.png
doudesu/assets/icons/loading-animation.png
doudesu/assets/images/logo.png
doudesu/core/__init__.py
doudesu/core/doudesu.py
doudesu/models/__init__.py
doudesu/models/manga.py
doudesu/ui/__init__.py
doudesu/ui/cli.py
doudesu/ui/gui.py
doudesu/ui/components/__init__.py
doudesu/ui/components/loading.py
doudesu/utils/__init__.py
doudesu/utils/constants.py
doudesu/utils/converter.py
doudesu-1.0.0.dist-info/METADATA
doudesu-1.0.0.dist-info/WHEEL
doudesu-1.0.0.dist-info/entry_points.txt
doudesu-1.0.0.dist-info/licenses/LICENSE
doudesu-1.0.0.dist-info/RECORD
