Metadata-Version: 2.3
Name: doudesu
Version: 1.0.0
Summary: A Python wrapper and downloader for doujindesu.tv
Project-URL: Homepage, https://github.com/MhankBarBar/doudesu
Project-URL: Repository, https://github.com/MhankBarBar/doudesu.git
Project-URL: Issues, https://github.com/MhankBarBar/doudesu/issues
Author-email: MhankBarBar <mhankbarbar@pm.me>
License: MIT License
Keywords: doujindesu,downloader,manga,pdf
Classifier: Development Status :: 5 - Production/Stable
Classifier: Intended Audience :: Developers
Classifier: License :: OSI Approved :: MIT License
Classifier: Operating System :: OS Independent
Classifier: Programming Language :: Python :: 3
Classifier: Programming Language :: Python :: 3.10
Classifier: Programming Language :: Python :: 3.11
Classifier: Programming Language :: Python :: 3.12
Classifier: Programming Language :: Python :: 3.13
Requires-Python: >=3.10
Requires-Dist: beautifulsoup4>=4.9.3
Requires-Dist: pillow>=8.0.0
Requires-Dist: pydantic>=2.0.0
Requires-Dist: reportlab>=4.0.0
Requires-Dist: rich>=10.0.0
Requires-Dist: tls-client>=0.2.1
Provides-Extra: api
Requires-Dist: fastapi>=0.109.0; extra == 'api'
Requires-Dist: uvicorn>=0.27.0; extra == 'api'
Provides-Extra: gui
Requires-Dist: flet>=0.21.1; extra == 'gui'
